ldif.py
ldif-4.2.5.dist-info/LICENSE
ldif-4.2.5.dist-info/METADATA
ldif-4.2.5.dist-info/WHEEL
ldif-4.2.5.dist-info/RECORD
