Metadata-Version: 2.1
Name: ldif
Version: 4.2.5
Summary: generate and parse LDIF data (see RFC 2849).
Home-page: https://github.com/abilian/ldif
License: BSD
Author: Abilian SAS
Author-email: dev@abilian.com
Requires-Python: >=3.9,<4.0
Classifier: Development Status :: 5 - Production/Stable
Classifier: Intended Audience :: Developers
Classifier: License :: OSI Approved :: BSD License
Classifier: License :: Other/Proprietary License
Classifier: Operating System :: OS Independent
Classifier: Programming Language :: Python
Classifier: Programming Language :: Python :: 3
Classifier: Programming Language :: Python :: 3.9
Classifier: Programming Language :: Python :: 3.10
Classifier: Programming Language :: Python :: 3.11
Classifier: Programming Language :: Python :: 3.12
Classifier: Topic :: System :: Systems Administration :: Authentication/Directory :: LDAP
Project-URL: Documentation, https://ldif.readthedocs.io/en/latest/
